[
  {
    "application_id": "AF-2026-0001",
    "submitted_ts": "2026-03-11T09:07:00",
    "queue_reason": "Manual Review - New Dealer",
    "applicant_name": "Jordan Patel",
    "province_state": "ON",
    "dealer_name": "Maple Leaf Motors",
    "dealer_id": "DLR-1137",
    "dealer_tier": "A",
    "dealer_region": "GTA",
    "bureau_score": 760,
    "gross_monthly_income": 6720,
    "other_monthly_debt": 790,
    "employment_status": "Full-time",
    "job_tenure_months": 18,
    "residence_tenure_months": 15,
    "prior_td_relationship_years": 3,
    "prior_auto_loan_paid_off_count": 1,
    "delinquencies_12m": 0,
    "bankruptcies_flag": false,
    "collections_flag": false,
    "recent_inquiries_6m": 2,
    "vehicle_year": 2023,
    "vehicle_make": "Toyota",
    "vehicle_model": "RAV4",
    "vin": "VIN01TDMOCK202600031",
    "mileage": 12000,
    "sale_price": 24200,
    "book_value": 23250,
    "salvage_flag": false,
    "requested_loan_amount": 21780.0,
    "cash_down_payment": 1120,
    "trade_in_value": 0,
    "term_months": 60,
    "apr": 6.15,
    "fees": 495,
    "taxes": 3146.0,
    "policy_thresholds": {
      "max_ltv": 1.1,
      "max_pti": 0.18,
      "max_dti": 0.42,
      "min_bureau": 640,
      "max_vehicle_age": 10,
      "max_mileage": 160000
    },
    "application_notes": "Mock scenario: clean approve.",
    "documentation_status": "Complete",
    "missing_docs": [],
    "verification_status": "Verified",
    "required_conditions": [],
    "underwriter_queue_status": "In Review",
    "sla_bucket": "8-24h",
    "funded_volume_td": 53,
    "historical_approval_rate": 0.71,
    "first_payment_default_rate": 0.011,
    "dealer_exception_rate": 0.1,
    "average_booked_risk_tier": "B",
    "dealer_watchlist_flag": false,
    "employment_history": "Stable employment narrative for demo.",
    "residence_stability": "Moderate residence profile.",
    "compensating_factors": [
      "Reasonable bureau",
      "No major derogatories",
      "Dealer quality acceptable"
    ],
    "vin_decode_match": true,
    "valuation_sources": [
      "Black Book",
      "Dealer appraisal"
    ],
    "prior_title_issue": "None",
    "mileage_reasonableness": "Within expected range",
    "age_term_reasonableness": "Reasonable",
    "collateral_quality_notes": "Demo collateral notes",
    "prior_policy_exceptions_count": 0,
    "underwriter_assignment": "UW-Team-2",
    "existing_auto_payment": 220,
    "baseline_recommendation": "approve",
    "case_segment": "clean approve",
    "application_timeline": [
      {
        "event_ts": "2026-03-11 09:07",
        "event": "Application submitted"
      },
      {
        "event_ts": "2026-03-11 09:13",
        "event": "Manual Review - New Dealer"
      },
      {
        "event_ts": "2026-03-11 09:19",
        "event": "Manual adjudication queue"
      }
    ]
  },
  {
    "application_id": "AF-2026-0002",
    "submitted_ts": "2026-03-11T10:14:00",
    "queue_reason": "High LTV",
    "applicant_name": "Avery Singh",
    "province_state": "BC",
    "dealer_name": "Pacific Drive Auto",
    "dealer_id": "DLR-1274",
    "dealer_tier": "B",
    "dealer_region": "Lower Mainland",
    "bureau_score": 728,
    "gross_monthly_income": 5840,
    "other_monthly_debt": 880,
    "employment_status": "Full-time",
    "job_tenure_months": 24,
    "residence_tenure_months": 20,
    "prior_td_relationship_years": 4,
    "prior_auto_loan_paid_off_count": 0,
    "delinquencies_12m": 1,
    "bankruptcies_flag": false,
    "collections_flag": false,
    "recent_inquiries_6m": 3,
    "vehicle_year": 2022,
    "vehicle_make": "Honda",
    "vehicle_model": "CR-V",
    "vin": "VIN02TDMOCK202600062",
    "mileage": 24000,
    "sale_price": 26400,
    "book_value": 25200,
    "salvage_flag": false,
    "requested_loan_amount": 23760.0,
    "cash_down_payment": 1340,
    "trade_in_value": 0,
    "term_months": 72,
    "apr": 6.5,
    "fees": 495,
    "taxes": 3432.0,
    "policy_thresholds": {
      "max_ltv": 1.12,
      "max_pti": 0.18,
      "max_dti": 0.42,
      "min_bureau": 640,
      "max_vehicle_age": 10,
      "max_mileage": 160000
    },
    "application_notes": "Mock scenario: strong conditional approval with increased down payment.",
    "documentation_status": "Complete",
    "missing_docs": [],
    "verification_status": "Verified",
    "required_conditions": [
      "Increase cash down payment by at least $2,500"
    ],
    "underwriter_queue_status": "In Review",
    "sla_bucket": "2-8h",
    "funded_volume_td": 66,
    "historical_approval_rate": 0.74,
    "first_payment_default_rate": 0.013,
    "dealer_exception_rate": 0.14,
    "average_booked_risk_tier": "C",
    "dealer_watchlist_flag": false,
    "employment_history": "Stable employment narrative for demo.",
    "residence_stability": "Stable residence profile.",
    "compensating_factors": [
      "Reasonable bureau",
      "No major derogatories",
      "Dealer quality acceptable"
    ],
    "vin_decode_match": true,
    "valuation_sources": [
      "Black Book",
      "Dealer appraisal"
    ],
    "prior_title_issue": "None",
    "mileage_reasonableness": "Within expected range",
    "age_term_reasonableness": "Reasonable",
    "collateral_quality_notes": "Demo collateral notes",
    "prior_policy_exceptions_count": 1,
    "underwriter_assignment": "UW-Team-3",
    "existing_auto_payment": 0,
    "baseline_recommendation": "conditional_approval",
    "case_segment": "strong conditional approval with increased down payment",
    "application_timeline": [
      {
        "event_ts": "2026-03-11 10:14",
        "event": "Application submitted"
      },
      {
        "event_ts": "2026-03-11 10:20",
        "event": "High LTV"
      },
      {
        "event_ts": "2026-03-11 10:26",
        "event": "Manual adjudication queue"
      }
    ]
  },
  {
    "application_id": "AF-2026-0003",
    "submitted_ts": "2026-03-11T10:21:00",
    "queue_reason": "Income Verification",
    "applicant_name": "Morgan Chen",
    "province_state": "AB",
    "dealer_name": "Prairie Auto Centre",
    "dealer_id": "DLR-1411",
    "dealer_tier": "B",
    "dealer_region": "Calgary",
    "bureau_score": 721,
    "gross_monthly_income": 6160,
    "other_monthly_debt": 970,
    "employment_status": "Contract",
    "job_tenure_months": 30,
    "residence_tenure_months": 25,
    "prior_td_relationship_years": 5,
    "prior_auto_loan_paid_off_count": 0,
    "delinquencies_12m": 1,
    "bankruptcies_flag": false,
    "collections_flag": false,
    "recent_inquiries_6m": 4,
    "vehicle_year": 2021,
    "vehicle_make": "Ford",
    "vehicle_model": "Escape",
    "vin": "VIN03TDMOCK202600093",
    "mileage": 36000,
    "sale_price": 28600,
    "book_value": 27150,
    "salvage_flag": false,
    "requested_loan_amount": 25740.0,
    "cash_down_payment": 1560,
    "trade_in_value": 0,
    "term_months": 72,
    "apr": 6.85,
    "fees": 495,
    "taxes": 3718.0,
    "policy_thresholds": {
      "max_ltv": 1.1,
      "max_pti": 0.18,
      "max_dti": 0.43,
      "min_bureau": 640,
      "max_vehicle_age": 10,
      "max_mileage": 160000
    },
    "application_notes": "Mock scenario: conditional approval requiring income verification.",
    "documentation_status": "Partial",
    "missing_docs": [
      "Latest paystub",
      "3 months bank statements"
    ],
    "verification_status": "Pending income validation",
    "required_conditions": [
      "Income verification",
      "Auto-pay enrollment"
    ],
    "underwriter_queue_status": "Awaiting Docs",
    "sla_bucket": "2-8h",
    "funded_volume_td": 79,
    "historical_approval_rate": 0.77,
    "first_payment_default_rate": 0.015,
    "dealer_exception_rate": 0.18,
    "average_booked_risk_tier": "D",
    "dealer_watchlist_flag": false,
    "employment_history": "Stable employment narrative for demo.",
    "residence_stability": "Moderate residence profile.",
    "compensating_factors": [
      "Reasonable bureau",
      "No major derogatories",
      "Dealer quality acceptable"
    ],
    "vin_decode_match": true,
    "valuation_sources": [
      "Black Book",
      "Dealer appraisal"
    ],
    "prior_title_issue": "None",
    "mileage_reasonableness": "Within expected range",
    "age_term_reasonableness": "Reasonable",
    "collateral_quality_notes": "Demo collateral notes",
    "prior_policy_exceptions_count": 1,
    "underwriter_assignment": "UW-Team-1",
    "existing_auto_payment": 260,
    "baseline_recommendation": "conditional_approval",
    "case_segment": "conditional approval requiring income verification",
    "application_timeline": [
      {
        "event_ts": "2026-03-11 10:21",
        "event": "Application submitted"
      },
      {
        "event_ts": "2026-03-11 10:27",
        "event": "Income Verification"
      },
      {
        "event_ts": "2026-03-11 10:33",
        "event": "Manual adjudication queue"
      }
    ]
  },
  {
    "application_id": "AF-2026-0004",
    "submitted_ts": "2026-03-11T11:28:00",
    "queue_reason": "Affordability Concern",
    "applicant_name": "Taylor Brooks",
    "province_state": "NS",
    "dealer_name": "Harbourline Auto",
    "dealer_id": "DLR-1548",
    "dealer_tier": "B",
    "dealer_region": "Atlantic",
    "bureau_score": 674,
    "gross_monthly_income": 5080,
    "other_monthly_debt": 1560,
    "employment_status": "Full-time",
    "job_tenure_months": 36,
    "residence_tenure_months": 30,
    "prior_td_relationship_years": 6,
    "prior_auto_loan_paid_off_count": 0,
    "delinquencies_12m": 3,
    "bankruptcies_flag": false,
    "collections_flag": true,
    "recent_inquiries_6m": 5,
    "vehicle_year": 2020,
    "vehicle_make": "Nissan",
    "vehicle_model": "Rogue",
    "vin": "VIN04TDMOCK202600124",
    "mileage": 48000,
    "sale_price": 30800,
    "book_value": 29100,
    "salvage_flag": false,
    "requested_loan_amount": 27720.0,
    "cash_down_payment": 1780,
    "trade_in_value": 500,
    "term_months": 60,
    "apr": 9.4,
    "fees": 595,
    "taxes": 4004.0,
    "policy_thresholds": {
      "max_ltv": 1.12,
      "max_pti": 0.18,
      "max_dti": 0.42,
      "min_bureau": 630,
      "max_vehicle_age": 10,
      "max_mileage": 160000
    },
    "application_notes": "Mock scenario: decline due to weak affordability + poor bureau.",
    "documentation_status": "Complete",
    "missing_docs": [],
    "verification_status": "Verified",
    "required_conditions": [],
    "underwriter_queue_status": "In Review",
    "sla_bucket": "Urgent <2h",
    "funded_volume_td": 92,
    "historical_approval_rate": 0.8,
    "first_payment_default_rate": 0.017,
    "dealer_exception_rate": 0.22,
    "average_booked_risk_tier": "A",
    "dealer_watchlist_flag": false,
    "employment_history": "Uneven employment narrative for demo.",
    "residence_stability": "Stable residence profile.",
    "compensating_factors": [
      "No material compensating factors"
    ],
    "vin_decode_match": true,
    "valuation_sources": [
      "Black Book",
      "Dealer appraisal"
    ],
    "prior_title_issue": "None",
    "mileage_reasonableness": "Within expected range",
    "age_term_reasonableness": "Reasonable",
    "collateral_quality_notes": "Demo collateral notes",
    "prior_policy_exceptions_count": 2,
    "underwriter_assignment": "UW-Team-2",
    "existing_auto_payment": 0,
    "baseline_recommendation": "decline",
    "case_segment": "decline due to weak affordability + poor bureau",
    "application_timeline": [
      {
        "event_ts": "2026-03-11 11:28",
        "event": "Application submitted"
      },
      {
        "event_ts": "2026-03-11 11:34",
        "event": "Affordability Concern"
      },
      {
        "event_ts": "2026-03-11 11:40",
        "event": "Manual adjudication queue"
      }
    ]
  },
  {
    "application_id": "AF-2026-0005",
    "submitted_ts": "2026-03-11T11:35:00",
    "queue_reason": "Borderline Ratios",
    "applicant_name": "Reese Thompson",
    "province_state": "MB",
    "dealer_name": "Prairie Lane Auto",
    "dealer_id": "DLR-1685",
    "dealer_tier": "A",
    "dealer_region": "Winnipeg",
    "bureau_score": 707,
    "gross_monthly_income": 6800,
    "other_monthly_debt": 1150,
    "employment_status": "Full-time",
    "job_tenure_months": 42,
    "residence_tenure_months": 35,
    "prior_td_relationship_years": 7,
    "prior_auto_loan_paid_off_count": 1,
    "delinquencies_12m": 1,
    "bankruptcies_flag": false,
    "collections_flag": false,
    "recent_inquiries_6m": 6,
    "vehicle_year": 2019,
    "vehicle_make": "Hyundai",
    "vehicle_model": "Santa Fe",
    "vin": "VIN05TDMOCK202600155",
    "mileage": 60000,
    "sale_price": 33000,
    "book_value": 31050,
    "salvage_flag": false,
    "requested_loan_amount": 29700.0,
    "cash_down_payment": 2000,
    "trade_in_value": 0,
    "term_months": 72,
    "apr": 7.55,
    "fees": 495,
    "taxes": 4290.0,
    "policy_thresholds": {
      "max_ltv": 1.1,
      "max_pti": 0.18,
      "max_dti": 0.42,
      "min_bureau": 640,
      "max_vehicle_age": 10,
      "max_mileage": 160000
    },
    "application_notes": "Mock scenario: borderline case with strong compensating factors.",
    "documentation_status": "Complete",
    "missing_docs": [],
    "verification_status": "Verified",
    "required_conditions": [],
    "underwriter_queue_status": "In Review",
    "sla_bucket": "8-24h",
    "funded_volume_td": 105,
    "historical_approval_rate": 0.83,
    "first_payment_default_rate": 0.019,
    "dealer_exception_rate": 0.08,
    "average_booked_risk_tier": "B",
    "dealer_watchlist_flag": false,
    "employment_history": "Stable employment narrative for demo.",
    "residence_stability": "Moderate residence profile.",
    "compensating_factors": [
      "Reasonable bureau",
      "No major derogatories",
      "Dealer quality acceptable"
    ],
    "vin_decode_match": true,
    "valuation_sources": [
      "Black Book",
      "Dealer appraisal"
    ],
    "prior_title_issue": "None",
    "mileage_reasonableness": "Within expected range",
    "age_term_reasonableness": "Reasonable",
    "collateral_quality_notes": "Demo collateral notes",
    "prior_policy_exceptions_count": 1,
    "underwriter_assignment": "UW-Team-3",
    "existing_auto_payment": 300,
    "baseline_recommendation": "conditional_approval",
    "case_segment": "borderline case with strong compensating factors",
    "application_timeline": [
      {
        "event_ts": "2026-03-11 11:35",
        "event": "Application submitted"
      },
      {
        "event_ts": "2026-03-11 11:41",
        "event": "Borderline Ratios"
      },
      {
        "event_ts": "2026-03-11 11:47",
        "event": "Manual adjudication queue"
      }
    ]
  },
  {
    "application_id": "AF-2026-0006",
    "submitted_ts": "2026-03-11T12:42:00",
    "queue_reason": "Dealer Risk Review",
    "applicant_name": "Casey Nguyen",
    "province_state": "QC",
    "dealer_name": "Metro Wheels Outlet",
    "dealer_id": "DLR-1822",
    "dealer_tier": "C",
    "dealer_region": "Montreal",
    "bureau_score": 700,
    "gross_monthly_income": 7120,
    "other_monthly_debt": 1240,
    "employment_status": "Full-time",
    "job_tenure_months": 48,
    "residence_tenure_months": 40,
    "prior_td_relationship_years": 0,
    "prior_auto_loan_paid_off_count": 0,
    "delinquencies_12m": 1,
    "bankruptcies_flag": false,
    "collections_flag": false,
    "recent_inquiries_6m": 1,
    "vehicle_year": 2018,
    "vehicle_make": "Mazda",
    "vehicle_model": "CX-5",
    "vin": "VIN06TDMOCK202600186",
    "mileage": 72000,
    "sale_price": 35200,
    "book_value": 33000,
    "salvage_flag": false,
    "requested_loan_amount": 31680.0,
    "cash_down_payment": 2220,
    "trade_in_value": 0,
    "term_months": 72,
    "apr": 7.9,
    "fees": 495,
    "taxes": 4576.0,
    "policy_thresholds": {
      "max_ltv": 1.12,
      "max_pti": 0.18,
      "max_dti": 0.43,
      "min_bureau": 640,
      "max_vehicle_age": 10,
      "max_mileage": 160000
    },
    "application_notes": "Mock scenario: dealer-risk-driven manual review.",
    "documentation_status": "Complete",
    "missing_docs": [],
    "verification_status": "Verified",
    "required_conditions": [],
    "underwriter_queue_status": "Escalated",
    "sla_bucket": "Urgent <2h",
    "funded_volume_td": 118,
    "historical_approval_rate": 0.86,
    "first_payment_default_rate": 0.009,
    "dealer_exception_rate": 0.12,
    "average_booked_risk_tier": "C",
    "dealer_watchlist_flag": true,
    "employment_history": "Stable employment narrative for demo.",
    "residence_stability": "Stable residence profile.",
    "compensating_factors": [
      "Reasonable bureau",
      "No major derogatories",
      "Dealer quality acceptable"
    ],
    "vin_decode_match": true,
    "valuation_sources": [
      "Black Book",
      "Dealer appraisal"
    ],
    "prior_title_issue": "None",
    "mileage_reasonableness": "Within expected range",
    "age_term_reasonableness": "Reasonable",
    "collateral_quality_notes": "Demo collateral notes",
    "prior_policy_exceptions_count": 3,
    "underwriter_assignment": "Senior-UW-Desk",
    "existing_auto_payment": 0,
    "baseline_recommendation": "conditional_approval",
    "case_segment": "dealer-risk-driven manual review",
    "application_timeline": [
      {
        "event_ts": "2026-03-11 12:42",
        "event": "Application submitted"
      },
      {
        "event_ts": "2026-03-11 12:48",
        "event": "Dealer Risk Review"
      },
      {
        "event_ts": "2026-03-11 12:54",
        "event": "Manual adjudication queue"
      }
    ]
  },
  {
    "application_id": "AF-2026-0007",
    "submitted_ts": "2026-03-11T12:49:00",
    "queue_reason": "Valuation Mismatch",
    "applicant_name": "Parker ONeill",
    "province_state": "ON",
    "dealer_name": "Northern Auto Hub",
    "dealer_id": "DLR-1959",
    "dealer_tier": "B",
    "dealer_region": "Ottawa",
    "bureau_score": 693,
    "gross_monthly_income": 7440,
    "other_monthly_debt": 1330,
    "employment_status": "Full-time",
    "job_tenure_months": 54,
    "residence_tenure_months": 45,
    "prior_td_relationship_years": 1,
    "prior_auto_loan_paid_off_count": 0,
    "delinquencies_12m": 1,
    "bankruptcies_flag": false,
    "collections_flag": false,
    "recent_inquiries_6m": 2,
    "vehicle_year": 2017,
    "vehicle_make": "Jeep",
    "vehicle_model": "Grand Cherokee",
    "vin": "VIN07TDMOCK202600217",
    "mileage": 84000,
    "sale_price": 37400,
    "book_value": 31450,
    "salvage_flag": false,
    "requested_loan_amount": 33660.0,
    "cash_down_payment": 2440,
    "trade_in_value": 0,
    "term_months": 60,
    "apr": 8.25,
    "fees": 495,
    "taxes": 4862.0,
    "policy_thresholds": {
      "max_ltv": 1.1,
      "max_pti": 0.18,
      "max_dti": 0.42,
      "min_bureau": 640,
      "max_vehicle_age": 10,
      "max_mileage": 160000
    },
    "application_notes": "Mock scenario: vehicle valuation mismatch case.",
    "documentation_status": "Partial",
    "missing_docs": [
      "Independent appraisal"
    ],
    "verification_status": "Pending collateral review",
    "required_conditions": [],
    "underwriter_queue_status": "In Review",
    "sla_bucket": "2-8h",
    "funded_volume_td": 131,
    "historical_approval_rate": 0.69,
    "first_payment_default_rate": 0.011,
    "dealer_exception_rate": 0.16,
    "average_booked_risk_tier": "D",
    "dealer_watchlist_flag": false,
    "employment_history": "Stable employment narrative for demo.",
    "residence_stability": "Moderate residence profile.",
    "compensating_factors": [
      "Reasonable bureau",
      "No major derogatories",
      "Dealer quality acceptable"
    ],
    "vin_decode_match": true,
    "valuation_sources": [
      "Black Book",
      "Dealer appraisal"
    ],
    "prior_title_issue": "None",
    "mileage_reasonableness": "Within expected range",
    "age_term_reasonableness": "Reasonable",
    "collateral_quality_notes": "Demo collateral notes",
    "prior_policy_exceptions_count": 2,
    "underwriter_assignment": "UW-Team-2",
    "existing_auto_payment": 340,
    "baseline_recommendation": "conditional_approval",
    "case_segment": "vehicle valuation mismatch case",
    "application_timeline": [
      {
        "event_ts": "2026-03-11 12:49",
        "event": "Application submitted"
      },
      {
        "event_ts": "2026-03-11 12:55",
        "event": "Valuation Mismatch"
      },
      {
        "event_ts": "2026-03-11 12:01",
        "event": "Manual adjudication queue"
      }
    ]
  },
  {
    "application_id": "AF-2026-0008",
    "submitted_ts": "2026-03-11T13:56:00",
    "queue_reason": "Age/Term Mismatch",
    "applicant_name": "Riley Adams",
    "province_state": "SK",
    "dealer_name": "Prairie Select Autos",
    "dealer_id": "DLR-2096",
    "dealer_tier": "B",
    "dealer_region": "Saskatoon",
    "bureau_score": 686,
    "gross_monthly_income": 7760,
    "other_monthly_debt": 1420,
    "employment_status": "Full-time",
    "job_tenure_months": 60,
    "residence_tenure_months": 50,
    "prior_td_relationship_years": 2,
    "prior_auto_loan_paid_off_count": 0,
    "delinquencies_12m": 1,
    "bankruptcies_flag": false,
    "collections_flag": false,
    "recent_inquiries_6m": 3,
    "vehicle_year": 2016,
    "vehicle_make": "Chevrolet",
    "vehicle_model": "Equinox",
    "vin": "VIN08TDMOCK202600248",
    "mileage": 96000,
    "sale_price": 39600,
    "book_value": 36900,
    "salvage_flag": false,
    "requested_loan_amount": 35640.0,
    "cash_down_payment": 2660,
    "trade_in_value": 500,
    "term_months": 84,
    "apr": 8.6,
    "fees": 595,
    "taxes": 5148.0,
    "policy_thresholds": {
      "max_ltv": 1.12,
      "max_pti": 0.18,
      "max_dti": 0.42,
      "min_bureau": 640,
      "max_vehicle_age": 10,
      "max_mileage": 160000
    },
    "application_notes": "Mock scenario: long-term / old-vehicle mismatch case.",
    "documentation_status": "Complete",
    "missing_docs": [],
    "verification_status": "Verified",
    "required_conditions": [
      "Shorten term to 60 months"
    ],
    "underwriter_queue_status": "In Review",
    "sla_bucket": "8-24h",
    "funded_volume_td": 144,
    "historical_approval_rate": 0.72,
    "first_payment_default_rate": 0.013,
    "dealer_exception_rate": 0.2,
    "average_booked_risk_tier": "A",
    "dealer_watchlist_flag": false,
    "employment_history": "Stable employment narrative for demo.",
    "residence_stability": "Stable residence profile.",
    "compensating_factors": [
      "Reasonable bureau",
      "No major derogatories",
      "Dealer quality acceptable"
    ],
    "vin_decode_match": true,
    "valuation_sources": [
      "Black Book",
      "Dealer appraisal"
    ],
    "prior_title_issue": "None",
    "mileage_reasonableness": "Within expected range",
    "age_term_reasonableness": "Not reasonable",
    "collateral_quality_notes": "Demo collateral notes",
    "prior_policy_exceptions_count": 2,
    "underwriter_assignment": "UW-Team-3",
    "existing_auto_payment": 0,
    "baseline_recommendation": "conditional_approval",
    "case_segment": "long-term / old-vehicle mismatch case",
    "application_timeline": [
      {
        "event_ts": "2026-03-11 13:56",
        "event": "Application submitted"
      },
      {
        "event_ts": "2026-03-11 13:02",
        "event": "Age/Term Mismatch"
      },
      {
        "event_ts": "2026-03-11 13:08",
        "event": "Manual adjudication queue"
      }
    ]
  },
  {
    "application_id": "AF-2026-0009",
    "submitted_ts": "2026-03-11T13:03:00",
    "queue_reason": "Mileage Exception",
    "applicant_name": "Skyler Martin",
    "province_state": "NB",
    "dealer_name": "East Coast Wheels",
    "dealer_id": "DLR-2233",
    "dealer_tier": "B",
    "dealer_region": "Atlantic",
    "bureau_score": 679,
    "gross_monthly_income": 8080,
    "other_monthly_debt": 1510,
    "employment_status": "Full-time",
    "job_tenure_months": 66,
    "residence_tenure_months": 55,
    "prior_td_relationship_years": 3,
    "prior_auto_loan_paid_off_count": 0,
    "delinquencies_12m": 1,
    "bankruptcies_flag": false,
    "collections_flag": false,
    "recent_inquiries_6m": 4,
    "vehicle_year": 2024,
    "vehicle_make": "Subaru",
    "vehicle_model": "Outback",
    "vin": "VIN09TDMOCK202600279",
    "mileage": 133000,
    "sale_price": 41800,
    "book_value": 38850,
    "salvage_flag": false,
    "requested_loan_amount": 37620.0,
    "cash_down_payment": 2880,
    "trade_in_value": 0,
    "term_months": 72,
    "apr": 8.95,
    "fees": 495,
    "taxes": 5434.0,
    "policy_thresholds": {
      "max_ltv": 1.1,
      "max_pti": 0.18,
      "max_dti": 0.43,
      "min_bureau": 640,
      "max_vehicle_age": 10,
      "max_mileage": 160000
    },
    "application_notes": "Mock scenario: high mileage exception review.",
    "documentation_status": "Complete",
    "missing_docs": [],
    "verification_status": "Verified",
    "required_conditions": [
      "Mechanical inspection report",
      "12-month warranty"
    ],
    "underwriter_queue_status": "In Review",
    "sla_bucket": "2-8h",
    "funded_volume_td": 157,
    "historical_approval_rate": 0.75,
    "first_payment_default_rate": 0.015,
    "dealer_exception_rate": 0.06,
    "average_booked_risk_tier": "B",
    "dealer_watchlist_flag": false,
    "employment_history": "Stable employment narrative for demo.",
    "residence_stability": "Moderate residence profile.",
    "compensating_factors": [
      "Reasonable bureau",
      "No major derogatories",
      "Dealer quality acceptable"
    ],
    "vin_decode_match": true,
    "valuation_sources": [
      "Black Book",
      "Dealer appraisal"
    ],
    "prior_title_issue": "None",
    "mileage_reasonableness": "Above policy threshold",
    "age_term_reasonableness": "Reasonable",
    "collateral_quality_notes": "Demo collateral notes",
    "prior_policy_exceptions_count": 1,
    "underwriter_assignment": "UW-Team-1",
    "existing_auto_payment": 380,
    "baseline_recommendation": "conditional_approval",
    "case_segment": "high mileage exception review",
    "application_timeline": [
      {
        "event_ts": "2026-03-11 13:03",
        "event": "Application submitted"
      },
      {
        "event_ts": "2026-03-11 13:09",
        "event": "Mileage Exception"
      },
      {
        "event_ts": "2026-03-11 13:15",
        "event": "Manual adjudication queue"
      }
    ]
  },
  {
    "application_id": "AF-2026-0010",
    "submitted_ts": "2026-03-11T14:10:00",
    "queue_reason": "Repeat Customer Review",
    "applicant_name": "Jamie Rivera",
    "province_state": "ON",
    "dealer_name": "Cityline Auto Group",
    "dealer_id": "DLR-2370",
    "dealer_tier": "A",
    "dealer_region": "GTA",
    "bureau_score": 697,
    "gross_monthly_income": 9600,
    "other_monthly_debt": 1600,
    "employment_status": "Full-time",
    "job_tenure_months": 72,
    "residence_tenure_months": 60,
    "prior_td_relationship_years": 9,
    "prior_auto_loan_paid_off_count": 2,
    "delinquencies_12m": 0,
    "bankruptcies_flag": false,
    "collections_flag": false,
    "recent_inquiries_6m": 5,
    "vehicle_year": 2023,
    "vehicle_make": "Kia",
    "vehicle_model": "Sorento",
    "vin": "VIN10TDMOCK202600310",
    "mileage": 120000,
    "sale_price": 44000,
    "book_value": 40800,
    "salvage_flag": false,
    "requested_loan_amount": 39600.0,
    "cash_down_payment": 3100,
    "trade_in_value": 0,
    "term_months": 60,
    "apr": 9.3,
    "fees": 495,
    "taxes": 5720.0,
    "policy_thresholds": {
      "max_ltv": 1.12,
      "max_pti": 0.18,
      "max_dti": 0.42,
      "min_bureau": 640,
      "max_vehicle_age": 10,
      "max_mileage": 160000
    },
    "application_notes": "Mock scenario: repeat customer with strong TD history.",
    "documentation_status": "Complete",
    "missing_docs": [],
    "verification_status": "Verified",
    "required_conditions": [],
    "underwriter_queue_status": "In Review",
    "sla_bucket": "8-24h",
    "funded_volume_td": 170,
    "historical_approval_rate": 0.78,
    "first_payment_default_rate": 0.017,
    "dealer_exception_rate": 0.1,
    "average_booked_risk_tier": "C",
    "dealer_watchlist_flag": false,
    "employment_history": "Stable employment narrative for demo.",
    "residence_stability": "Stable residence profile.",
    "compensating_factors": [
      "Excellent TD relationship",
      "Prior paid-off loans",
      "Strong capacity"
    ],
    "vin_decode_match": true,
    "valuation_sources": [
      "Black Book",
      "Dealer appraisal"
    ],
    "prior_title_issue": "None",
    "mileage_reasonableness": "Within expected range",
    "age_term_reasonableness": "Reasonable",
    "collateral_quality_notes": "Demo collateral notes",
    "prior_policy_exceptions_count": 0,
    "underwriter_assignment": "UW-Team-2",
    "existing_auto_payment": 0,
    "baseline_recommendation": "approve",
    "case_segment": "repeat customer with strong TD history",
    "application_timeline": [
      {
        "event_ts": "2026-03-11 14:10",
        "event": "Application submitted"
      },
      {
        "event_ts": "2026-03-11 14:16",
        "event": "Repeat Customer Review"
      },
      {
        "event_ts": "2026-03-11 14:22",
        "event": "Manual adjudication queue"
      }
    ]
  },
  {
    "application_id": "AF-2026-0011",
    "submitted_ts": "2026-03-11T14:17:00",
    "queue_reason": "Documentation Incomplete",
    "applicant_name": "Drew Wallace",
    "province_state": "AB",
    "dealer_name": "Mountain Ridge Auto",
    "dealer_id": "DLR-2507",
    "dealer_tier": "A",
    "dealer_region": "Edmonton",
    "bureau_score": 665,
    "gross_monthly_income": 8720,
    "other_monthly_debt": 1690,
    "employment_status": "Full-time",
    "job_tenure_months": 78,
    "residence_tenure_months": 65,
    "prior_td_relationship_years": 5,
    "prior_auto_loan_paid_off_count": 1,
    "delinquencies_12m": 1,
    "bankruptcies_flag": false,
    "collections_flag": false,
    "recent_inquiries_6m": 6,
    "vehicle_year": 2022,
    "vehicle_make": "Volkswagen",
    "vehicle_model": "Tiguan",
    "vin": "VIN11TDMOCK202600341",
    "mileage": 132000,
    "sale_price": 46200,
    "book_value": 42750,
    "salvage_flag": false,
    "requested_loan_amount": 41580.0,
    "cash_down_payment": 3320,
    "trade_in_value": 0,
    "term_months": 72,
    "apr": 9.65,
    "fees": 495,
    "taxes": 6006.0,
    "policy_thresholds": {
      "max_ltv": 1.1,
      "max_pti": 0.18,
      "max_dti": 0.42,
      "min_bureau": 640,
      "max_vehicle_age": 10,
      "max_mileage": 160000
    },
    "application_notes": "Mock scenario: incomplete documentation case.",
    "documentation_status": "Incomplete",
    "missing_docs": [
      "Proof of address",
      "Insurance binder",
      "Signed bill of sale"
    ],
    "verification_status": "Pending docs",
    "required_conditions": [
      "Collect and verify all missing docs"
    ],
    "underwriter_queue_status": "Awaiting Docs",
    "sla_bucket": "2-8h",
    "funded_volume_td": 183,
    "historical_approval_rate": 0.81,
    "first_payment_default_rate": 0.019,
    "dealer_exception_rate": 0.14,
    "average_booked_risk_tier": "D",
    "dealer_watchlist_flag": false,
    "employment_history": "Stable employment narrative for demo.",
    "residence_stability": "Moderate residence profile.",
    "compensating_factors": [
      "Reasonable bureau",
      "No major derogatories",
      "Dealer quality acceptable"
    ],
    "vin_decode_match": true,
    "valuation_sources": [
      "Black Book",
      "Dealer appraisal"
    ],
    "prior_title_issue": "None",
    "mileage_reasonableness": "Within expected range",
    "age_term_reasonableness": "Reasonable",
    "collateral_quality_notes": "Demo collateral notes",
    "prior_policy_exceptions_count": 1,
    "underwriter_assignment": "UW-Team-3",
    "existing_auto_payment": 420,
    "baseline_recommendation": "conditional_approval",
    "case_segment": "incomplete documentation case",
    "application_timeline": [
      {
        "event_ts": "2026-03-11 14:17",
        "event": "Application submitted"
      },
      {
        "event_ts": "2026-03-11 14:23",
        "event": "Documentation Incomplete"
      },
      {
        "event_ts": "2026-03-11 14:29",
        "event": "Manual adjudication queue"
      }
    ]
  },
  {
    "application_id": "AF-2026-0012",
    "submitted_ts": "2026-03-11T15:24:00",
    "queue_reason": "High LTV / Strong Income",
    "applicant_name": "Quinn Foster",
    "province_state": "BC",
    "dealer_name": "Westview Auto Mart",
    "dealer_id": "DLR-2644",
    "dealer_tier": "B",
    "dealer_region": "Vancouver Island",
    "bureau_score": 658,
    "gross_monthly_income": 10640,
    "other_monthly_debt": 1780,
    "employment_status": "Full-time",
    "job_tenure_months": 84,
    "residence_tenure_months": 70,
    "prior_td_relationship_years": 6,
    "prior_auto_loan_paid_off_count": 1,
    "delinquencies_12m": 1,
    "bankruptcies_flag": false,
    "collections_flag": false,
    "recent_inquiries_6m": 1,
    "vehicle_year": 2021,
    "vehicle_make": "Ford",
    "vehicle_model": "F-150",
    "vin": "VIN12TDMOCK202600372",
    "mileage": 144000,
    "sale_price": 48400,
    "book_value": 44700,
    "salvage_flag": false,
    "requested_loan_amount": 43560.0,
    "cash_down_payment": 3540,
    "trade_in_value": 500,
    "term_months": 72,
    "apr": 10.0,
    "fees": 595,
    "taxes": 6292.0,
    "policy_thresholds": {
      "max_ltv": 1.12,
      "max_pti": 0.18,
      "max_dti": 0.43,
      "min_bureau": 640,
      "max_vehicle_age": 10,
      "max_mileage": 160000
    },
    "application_notes": "Mock scenario: high LTV but strong income case.",
    "documentation_status": "Complete",
    "missing_docs": [],
    "verification_status": "Verified",
    "required_conditions": [
      "Additional $3,000 down payment"
    ],
    "underwriter_queue_status": "In Review",
    "sla_bucket": "8-24h",
    "funded_volume_td": 196,
    "historical_approval_rate": 0.84,
    "first_payment_default_rate": 0.009,
    "dealer_exception_rate": 0.18,
    "average_booked_risk_tier": "A",
    "dealer_watchlist_flag": false,
    "employment_history": "Stable employment narrative for demo.",
    "residence_stability": "Stable residence profile.",
    "compensating_factors": [
      "Strong income",
      "Long tenure",
      "Healthy residual income"
    ],
    "vin_decode_match": true,
    "valuation_sources": [
      "Black Book",
      "Dealer appraisal"
    ],
    "prior_title_issue": "None",
    "mileage_reasonableness": "Within expected range",
    "age_term_reasonableness": "Reasonable",
    "collateral_quality_notes": "Demo collateral notes",
    "prior_policy_exceptions_count": 1,
    "underwriter_assignment": "UW-Team-1",
    "existing_auto_payment": 0,
    "baseline_recommendation": "conditional_approval",
    "case_segment": "high LTV but strong income case",
    "application_timeline": [
      {
        "event_ts": "2026-03-11 15:24",
        "event": "Application submitted"
      },
      {
        "event_ts": "2026-03-11 15:30",
        "event": "High LTV / Strong Income"
      },
      {
        "event_ts": "2026-03-11 15:36",
        "event": "Manual adjudication queue"
      }
    ]
  },
  {
    "application_id": "AF-2026-0013",
    "submitted_ts": "2026-03-11T15:31:00",
    "queue_reason": "Policy Exception Review",
    "applicant_name": "Alex Morgan",
    "province_state": "ON",
    "dealer_name": "Union Auto Exchange",
    "dealer_id": "DLR-2781",
    "dealer_tier": "B",
    "dealer_region": "GTA",
    "bureau_score": 651,
    "gross_monthly_income": 9360,
    "other_monthly_debt": 1870,
    "employment_status": "Self-employed",
    "job_tenure_months": 90,
    "residence_tenure_months": 75,
    "prior_td_relationship_years": 7,
    "prior_auto_loan_paid_off_count": 0,
    "delinquencies_12m": 1,
    "bankruptcies_flag": false,
    "collections_flag": false,
    "recent_inquiries_6m": 2,
    "vehicle_year": 2020,
    "vehicle_make": "BMW",
    "vehicle_model": "X3",
    "vin": "VIN13TDMOCK202600403",
    "mileage": 156000,
    "sale_price": 50600,
    "book_value": 46650,
    "salvage_flag": false,
    "requested_loan_amount": 45540.0,
    "cash_down_payment": 3760,
    "trade_in_value": 0,
    "term_months": 60,
    "apr": 10.35,
    "fees": 495,
    "taxes": 6578.0,
    "policy_thresholds": {
      "max_ltv": 1.1,
      "max_pti": 0.18,
      "max_dti": 0.42,
      "min_bureau": 640,
      "max_vehicle_age": 10,
      "max_mileage": 140000
    },
    "application_notes": "Mock scenario: policy-exception-like case.",
    "documentation_status": "Partial",
    "missing_docs": [
      "2 years NOA",
      "Business financial summary"
    ],
    "verification_status": "Verified",
    "required_conditions": [
      "Income validation",
      "Term reduction",
      "Higher down payment"
    ],
    "underwriter_queue_status": "Escalated",
    "sla_bucket": "Urgent <2h",
    "funded_volume_td": 209,
    "historical_approval_rate": 0.87,
    "first_payment_default_rate": 0.011,
    "dealer_exception_rate": 0.22,
    "average_booked_risk_tier": "B",
    "dealer_watchlist_flag": false,
    "employment_history": "Stable employment narrative for demo.",
    "residence_stability": "Moderate residence profile.",
    "compensating_factors": [
      "Reasonable bureau",
      "No major derogatories",
      "Dealer quality acceptable"
    ],
    "vin_decode_match": true,
    "valuation_sources": [
      "Black Book",
      "Dealer appraisal"
    ],
    "prior_title_issue": "None",
    "mileage_reasonableness": "Within expected range",
    "age_term_reasonableness": "Reasonable",
    "collateral_quality_notes": "Demo collateral notes",
    "prior_policy_exceptions_count": 4,
    "underwriter_assignment": "Senior-UW-Desk",
    "existing_auto_payment": 460,
    "baseline_recommendation": "conditional_approval",
    "case_segment": "policy-exception-like case",
    "application_timeline": [
      {
        "event_ts": "2026-03-11 15:31",
        "event": "Application submitted"
      },
      {
        "event_ts": "2026-03-11 15:37",
        "event": "Policy Exception Review"
      },
      {
        "event_ts": "2026-03-11 15:43",
        "event": "Manual adjudication queue"
      }
    ]
  },
  {
    "application_id": "AF-2026-0014",
    "submitted_ts": "2026-03-11T16:38:00",
    "queue_reason": "Thin File / Luxury",
    "applicant_name": "Kai Bennett",
    "province_state": "QC",
    "dealer_name": "Prestige Auto Gallery",
    "dealer_id": "DLR-2918",
    "dealer_tier": "B",
    "dealer_region": "Montreal",
    "bureau_score": 644,
    "gross_monthly_income": 9680,
    "other_monthly_debt": 1960,
    "employment_status": "Full-time",
    "job_tenure_months": 96,
    "residence_tenure_months": 80,
    "prior_td_relationship_years": 0,
    "prior_auto_loan_paid_off_count": 0,
    "delinquencies_12m": 1,
    "bankruptcies_flag": false,
    "collections_flag": false,
    "recent_inquiries_6m": 5,
    "vehicle_year": 2019,
    "vehicle_make": "Mercedes-Benz",
    "vehicle_model": "GLC 300",
    "vin": "VIN14TDMOCK202600434",
    "mileage": 168000,
    "sale_price": 61800,
    "book_value": 57600,
    "salvage_flag": false,
    "requested_loan_amount": 55620.0,
    "cash_down_payment": 3980,
    "trade_in_value": 0,
    "term_months": 84,
    "apr": 10.7,
    "fees": 495,
    "taxes": 8034.0,
    "policy_thresholds": {
      "max_ltv": 1.12,
      "max_pti": 0.18,
      "max_dti": 0.42,
      "min_bureau": 640,
      "max_vehicle_age": 8,
      "max_mileage": 130000
    },
    "application_notes": "Mock scenario: luxury vehicle / thin-file case.",
    "documentation_status": "Complete",
    "missing_docs": [],
    "verification_status": "Verified",
    "required_conditions": [
      "Increase down payment",
      "Reduce term to 72 months"
    ],
    "underwriter_queue_status": "In Review",
    "sla_bucket": "2-8h",
    "funded_volume_td": 222,
    "historical_approval_rate": 0.7,
    "first_payment_default_rate": 0.013,
    "dealer_exception_rate": 0.08,
    "average_booked_risk_tier": "C",
    "dealer_watchlist_flag": false,
    "employment_history": "Stable employment narrative for demo.",
    "residence_stability": "Stable residence profile.",
    "compensating_factors": [
      "Reasonable bureau",
      "No major derogatories",
      "Dealer quality acceptable"
    ],
    "vin_decode_match": true,
    "valuation_sources": [
      "Black Book",
      "Dealer appraisal"
    ],
    "prior_title_issue": "None",
    "mileage_reasonableness": "Within expected range",
    "age_term_reasonableness": "Reasonable",
    "collateral_quality_notes": "Demo collateral notes",
    "prior_policy_exceptions_count": 1,
    "underwriter_assignment": "UW-Team-3",
    "existing_auto_payment": 0,
    "baseline_recommendation": "conditional_approval",
    "case_segment": "luxury vehicle / thin-file case",
    "application_timeline": [
      {
        "event_ts": "2026-03-11 16:38",
        "event": "Application submitted"
      },
      {
        "event_ts": "2026-03-11 16:44",
        "event": "Thin File / Luxury"
      },
      {
        "event_ts": "2026-03-11 16:50",
        "event": "Manual adjudication queue"
      }
    ]
  },
  {
    "application_id": "AF-2026-0015",
    "submitted_ts": "2026-03-11T16:45:00",
    "queue_reason": "Prime Fast Track",
    "applicant_name": "Cameron Lee",
    "province_state": "ON",
    "dealer_name": "Summit Auto Plaza",
    "dealer_id": "DLR-3055",
    "dealer_tier": "A",
    "dealer_region": "Hamilton",
    "bureau_score": 662,
    "gross_monthly_income": 11200,
    "other_monthly_debt": 2050,
    "employment_status": "Full-time",
    "job_tenure_months": 102,
    "residence_tenure_months": 85,
    "prior_td_relationship_years": 6,
    "prior_auto_loan_paid_off_count": 2,
    "delinquencies_12m": 0,
    "bankruptcies_flag": false,
    "collections_flag": false,
    "recent_inquiries_6m": 4,
    "vehicle_year": 2018,
    "vehicle_make": "Lexus",
    "vehicle_model": "NX 350",
    "vin": "VIN15TDMOCK202600465",
    "mileage": 180000,
    "sale_price": 55000,
    "book_value": 50550,
    "salvage_flag": false,
    "requested_loan_amount": 49500.0,
    "cash_down_payment": 4200,
    "trade_in_value": 0,
    "term_months": 72,
    "apr": 11.05,
    "fees": 495,
    "taxes": 7150.0,
    "policy_thresholds": {
      "max_ltv": 1.1,
      "max_pti": 0.16999999999999998,
      "max_dti": 0.43,
      "min_bureau": 680,
      "max_vehicle_age": 8,
      "max_mileage": 140000
    },
    "application_notes": "Mock scenario: prime applicant / straightforward approve.",
    "documentation_status": "Complete",
    "missing_docs": [],
    "verification_status": "Verified",
    "required_conditions": [],
    "underwriter_queue_status": "In Review",
    "sla_bucket": "8-24h",
    "funded_volume_td": 235,
    "historical_approval_rate": 0.73,
    "first_payment_default_rate": 0.015,
    "dealer_exception_rate": 0.12,
    "average_booked_risk_tier": "D",
    "dealer_watchlist_flag": false,
    "employment_history": "Stable employment narrative for demo.",
    "residence_stability": "Moderate residence profile.",
    "compensating_factors": [
      "Strong income",
      "Long tenure",
      "Healthy residual income"
    ],
    "vin_decode_match": true,
    "valuation_sources": [
      "Black Book",
      "Dealer appraisal"
    ],
    "prior_title_issue": "None",
    "mileage_reasonableness": "Within expected range",
    "age_term_reasonableness": "Reasonable",
    "collateral_quality_notes": "Demo collateral notes",
    "prior_policy_exceptions_count": 0,
    "underwriter_assignment": "UW-Team-1",
    "existing_auto_payment": 500,
    "baseline_recommendation": "approve",
    "case_segment": "prime applicant / straightforward approve",
    "application_timeline": [
      {
        "event_ts": "2026-03-11 16:45",
        "event": "Application submitted"
      },
      {
        "event_ts": "2026-03-11 16:51",
        "event": "Prime Fast Track"
      },
      {
        "event_ts": "2026-03-11 16:57",
        "event": "Manual adjudication queue"
      }
    ]
  }
]